verse/identity/authentication/__init__.py
verse/identity/authentication/_models.py
verse/identity/authentication/component.py
verse/identity/authentication/providers/api_key.py
verse/identity/authentication/providers/api_key_in_store.py
verse/identity/authentication/providers/auth0.py
verse/identity/authentication/providers/default.py
verse/identity/authentication/providers/mock.py
verse/identity/authentication/providers/msal.py
verse/identity/authentication/py.typed
verse_identity-0.0.28.dist-info/LICENSE
verse_identity-0.0.28.dist-info/METADATA
verse_identity-0.0.28.dist-info/WHEEL
verse_identity-0.0.28.dist-info/RECORD
