Metadata-Version: 2.3
Name: verse-identity
Version: 0.0.28
Summary: Verse Identity Components
License: MIT
Keywords: verse,identity,components
Author: Verse
Author-email: admin@rapidverse.com
Requires-Python: >=3.9
Classifier: License :: OSI Approved :: MIT License
Classifier: Programming Language :: Python :: 3
Classifier: Programming Language :: Python :: 3.9
Classifier: Programming Language :: Python :: 3.10
Classifier: Programming Language :: Python :: 3.11
Classifier: Programming Language :: Python :: 3.12
Classifier: Programming Language :: Python :: 3.13
Provides-Extra: all
Provides-Extra: authentication-auth0
Provides-Extra: authentication-default
Provides-Extra: authentication-mock
Requires-Dist: httpx ; extra == "authentication-auth0" or extra == "all"
Requires-Dist: pyjwt[crypto] ; extra == "authentication-auth0" or extra == "all"
Project-URL: Documentation, https://github.com/rapidverse/verse
Project-URL: Homepage, https://github.com/rapidverse/verse
Project-URL: Repository, https://github.com/rapidverse/verse
